daymark/__init__.py
daymark/daymark.py
daymark-1.1.12.dist-info/LICENSE.txt
daymark-1.1.12.dist-info/METADATA
daymark-1.1.12.dist-info/WHEEL
daymark-1.1.12.dist-info/top_level.txt
daymark-1.1.12.dist-info/RECORD
