Metadata-Version: 2.1
Name: daymark
Version: 1.1.12
Summary: daymark is a helper package.
Home-page: https://gitlab.com/aman.indshine/lighthouse-function-helper.git
Author: Samarthya Choudhary
Author-email: samarthyachoudhary7@gmail.com
License: MIT
Platform: UNKNOWN
Classifier: Development Status :: 3 - Alpha
Classifier: Intended Audience :: Developers
Classifier: Topic :: Software Development :: Build Tools
Classifier: License :: OSI Approved :: MIT License
Requires-Dist: requests
Requires-Dist: redis
